roche_datachapter_team_lib/__domain__.py
roche_datachapter_team_lib/__init__.py
roche_datachapter_team_lib/appsheet_service.py
roche_datachapter_team_lib/data_transformer.py
roche_datachapter_team_lib/db_config.py
roche_datachapter_team_lib/email_service.py
roche_datachapter_team_lib/excel_service.py
roche_datachapter_team_lib/google_services.py
roche_datachapter_team_lib/google_services_enums.py
roche_datachapter_team_lib/job_manager.py
roche_datachapter_team_lib/logger.py
roche_datachapter_team_lib/query_manager.py
roche_datachapter_team_lib/result_type.py
roche_datachapter_team_lib-0.0.12.dist-info/METADATA
roche_datachapter_team_lib-0.0.12.dist-info/WHEEL
roche_datachapter_team_lib-0.0.12.dist-info/licenses/LICENSE
roche_datachapter_team_lib-0.0.12.dist-info/RECORD
