Metadata-Version: 2.4
Name: roche_datachapter_team_lib
Version: 0.0.12
Summary: Modular Python library designed for building and managing robust ETL processes. Includes database connectors, Google Sheets/Drive integration, AppSheet API support, job scheduling via SQL Server Agent, Excel generation, and logging utilities.
Project-URL: Homepage, https://github.com/pypa/sampleproject
Project-URL: Issues, https://github.com/pypa/sampleproject/issues
Author-email: Lucas Frías <lucasmatiasfrias@live.com>, Uciel Bustamante <ucibustamante.a@gmail.com>
Maintainer-email: Uciel Bustamante <uciel.bustamante@contractors.roche.com>, Ignacio Castillo <ignacio.castillo@roche.com>, Diego Pedro <diego.pedro@contractors.roche.com>, Sara Fernandez <sara.fernandez.sf1@roche.com>
License-File: LICENSE
Classifier: License :: OSI Approved :: MIT License
Classifier: Operating System :: OS Independent
Classifier: Programming Language :: Python :: 3.12
Requires-Python: >=3.12
Requires-Dist: chardet==5.2.0
Requires-Dist: flask-sqlalchemy==3.0.3
Requires-Dist: flask==2.3.1
Requires-Dist: google-api-python-client==2.99.0
Requires-Dist: google-auth-httplib2==0.1.1
Requires-Dist: google-auth-oauthlib==1.1.0
Requires-Dist: openpyxl==3.1.2
Requires-Dist: oracledb==2.0.0
Requires-Dist: pandas==2.1.3
Requires-Dist: psycopg
Requires-Dist: psycopg-binary
Requires-Dist: pymssql
Requires-Dist: pymysql==1.1.0
Requires-Dist: pyodbc==5.0.1
Requires-Dist: requests==2.31.0
Requires-Dist: snowflake-connector-python==3.15.0
Requires-Dist: snowflake-sqlalchemy==1.7.3
Requires-Dist: sqlalchemy-hana==1.1.1
Requires-Dist: sqlalchemy==2.0.30
